dialogflow_response/__init__.py
dialogflow_response/response.py
tests/__init__.py
tests/test_card_response.py
tests/test_choices_response.py
tests/test_fulfillment_response.py
tests/test_image_response.py
tests/test_request_location_response.py
tests/test_simple_response.py
dialogflow_response-0.1.2.dist-info/LICENCE
dialogflow_response-0.1.2.dist-info/METADATA
dialogflow_response-0.1.2.dist-info/WHEEL
dialogflow_response-0.1.2.dist-info/top_level.txt
dialogflow_response-0.1.2.dist-info/RECORD
