Metadata-Version: 2.1
Name: dialogflow-response
Version: 0.1.2
Summary: Create webhook responses for Dialogflow with this small library in python.
Home-page: https://github.com/bruino/dialogflow-response
Author: bruino
Author-email: bruno.sarverry@outlook.com
License: UNKNOWN
Platform: UNKNOWN
Classifier: Programming Language :: Python :: 3
Classifier: License :: OSI Approved :: GNU General Public License v3 (GPLv3)
Classifier: Operating System :: OS Independent
Requires-Python: >=3.6
